LICENSE
README.md
setup.py
disnake/ext/invitetracker/__init__.py
disnake/ext/invitetracker/invite_tracker.py
disnake_ext_invitetracker.egg-info/PKG-INFO
disnake_ext_invitetracker.egg-info/SOURCES.txt
disnake_ext_invitetracker.egg-info/dependency_links.txt
disnake_ext_invitetracker.egg-info/requires.txt
disnake_ext_invitetracker.egg-info/top_level.txt