Metadata-Version: 2.1
Name: disnake-ext-invitetracker
Version: 1.0
Summary: A module that allows you to track invitations
Home-page: https://github.com/earluv/disnake-ext-invitetracker
Author: Lukef
License: Apache Software License
Project-URL: Source, https://github.com/earluv/disnake-ext-invitetracker
Classifier: Development Status :: 5 - Production/Stable
Classifier: Framework :: AsyncIO
Classifier: Intended Audience :: Developers
Classifier: License :: OSI Approved :: Apache Software License
Classifier: Natural Language :: English
Classifier: Operating System :: OS Independent
Classifier: Programming Language :: Python
Classifier: Programming Language :: Python :: 3
Classifier: Programming Language :: Python :: 3 :: Only
Classifier: Programming Language :: Python :: 3.8
Classifier: Programming Language :: Python :: 3.9
Classifier: Programming Language :: Python :: 3.10
Classifier: Programming Language :: Python :: Implementation :: CPython
Classifier: Topic :: Communications
Classifier: Topic :: Documentation
Classifier: Topic :: Documentation :: Sphinx
Classifier: Topic :: Internet
Classifier: Topic :: Software Development
Classifier: Topic :: Software Development :: Libraries
Classifier: Topic :: Software Development :: Libraries :: Python Modules
Requires-Python: >=3.8.0
License-File: LICENSE
Provides-Extra: docs
Requires-Dist: sphinx; extra == "docs"
Requires-Dist: sphinxcontrib_trio; extra == "docs"
Requires-Dist: sphinx-rtd-theme; extra == "docs"
